setup.cfg
setup.py
win10batteryoptimizer/__init__.py
win10batteryoptimizer/__main__.py
win10batteryoptimizer.egg-info/PKG-INFO
win10batteryoptimizer.egg-info/SOURCES.txt
win10batteryoptimizer.egg-info/dependency_links.txt
win10batteryoptimizer.egg-info/requires.txt
win10batteryoptimizer.egg-info/top_level.txt