Metadata-Version: 1.1
Name: win10batteryoptimizer
Version: 0.1.1
Summary: An easy-to-use Python library for maintaing the optimal battery life for windows 10
Home-page: https://github.com/arunkumarpalaniappan/win10batteryoptimizer
Author: Arunkumar Palaniappan
Author-email: akrp@live.in
License: MIT
Download-URL: https://github.com/arunkumarpalaniappan/win10batteryoptimizer/tarball/0.0.1
Platform: UNKNOWN
Classifier: Development Status :: 3 - Alpha
Classifier: Topic :: Utilities
Classifier: Operating System :: Microsoft
Classifier: Environment :: Win32 (MS Windows)
Classifier: License :: OSI Approved :: MIT License
